datadelta/__init__.py
datadelta/datadelta.py
datadelta/data/EqualDataFrames_new_df.csv
datadelta/data/EqualDataFrames_old_df.csv
datadelta/data/MainTestData_new_df.csv
datadelta/data/MainTestData_old_df.csv
datadelta/data/RemovedColumns_new_df.csv
datadelta/data/RemovedColumns_old_df.csv
datadelta/data/correct_column_subset_report.pickle
datadelta/data/correct_consolidated_report.pickle
datadelta/data/datadelta_html_report.html
datadelta-0.0.2.dist-info/LICENSE.txt
datadelta-0.0.2.dist-info/METADATA
datadelta-0.0.2.dist-info/WHEEL
datadelta-0.0.2.dist-info/top_level.txt
datadelta-0.0.2.dist-info/RECORD
