Metadata-Version: 2.1
Name: datadelta
Version: 0.0.2
Summary: The best Python package for comparing two dataframes
Home-page: https://github.com/gibbsbravo/DataDelta
Author: Andrew Gibbs-Bravo
Author-email: andrewgbravo@gmail.com
License: UNKNOWN
Keywords: python,dataops,devops,data,data analysis
Platform: UNKNOWN
Classifier: Programming Language :: Python :: 3
Classifier: Programming Language :: Python :: 3.7
Classifier: Programming Language :: Python :: 3.8
Classifier: License :: OSI Approved :: GNU General Public License v3 (GPLv3)
Classifier: Operating System :: OS Independent
License-File: LICENSE.txt
Requires-Dist: pandas (>=1.0.0)
Requires-Dist: numpy
Requires-Dist: jinja2
Provides-Extra: dev
Requires-Dist: pytest ; extra == 'dev'
Requires-Dist: check-manifest ; extra == 'dev'
